{"19dc03b5-97e2-5532-ab83-d3af5cf95700":{"reqTiles":["Up","Left"],"inputs":[{"x":0.2,"y":0.0,"balls":[{"type":1,"rate":0.36163330078125}]},{"x":0.0,"y":0.65,"balls":[{"type":2,"rate":0.5294392903645834}]}],"outputs":[{"x":0.65,"y":1.0,"balls":[{"type":2,"rate":0.5294392903645834}]},{"x":0.0,"y":0.8,"balls":[{"type":1,"rate":0.36090087890625}]}],"spec":{}},"5a509277-26c0-5565-9be2-b2aa1fbcfb2a":{"reqTiles":["Up","Left"],"inputs":[{"x":0.65,"y":0.0,"balls":[{"type":1,"rate":0.36163330078125}]},{"x":0.0,"y":0.65,"balls":[{"type":4,"rate":0.83203125}]},{"x":1.0,"y":0.8,"balls":[{"type":3,"rate":0.5791015625}]}],"outputs":[{"x":0.65,"y":1.0,"balls":[{"type":4,"rate":0.83203125}]},{"x":0.0,"y":0.8,"balls":[{"type":3,"rate":0.5791015625}]},{"x":1.0,"y":0.35,"balls":[{"type":1,"rate":0.36090087890625}]}],"spec":{}},"c3fe4648-0c6e-5020-a27d-976cfb50a31c":{"reqTiles":["Up","Left"],"inputs":[{"x":0.65,"y":0.0,"balls":[{"type":4,"rate":0.83203125}]},{"x":0.0,"y":0.35,"balls":[{"type":2,"rate":0.26906331380208337}]},{"x":0.0,"y":0.65,"balls":[{"type":3,"rate":0.5791015625}]},{"x":1.0,"y":0.35,"balls":[{"type":1,"rate":0.36163330078125}]}],"outputs":[{"x":0.5,"y":1.0,"balls":[{"type":3,"rate":0.5791015625}]},{"x":0.0,"y":0.2,"balls":[{"type":4,"rate":0.83203125}]},{"x":0.0,"y":0.5,"balls":[{"type":1,"rate":0.36090087890625}]},{"x":1.0,"y":0.5,"balls":[{"type":2,"rate":0.26906331380208337}]}],"spec":{}},"810398ea-03cf-5558-8aa2-96d24af02191":{"reqTiles":["Up"],"inputs":[{"x":0.5,"y":0.0,"balls":[{"type":4,"rate":0.8359375}]}],"outputs":[{"x":0.65,"y":1.0,"balls":[{"type":4,"rate":0.8359375}]}],"spec":{}},"05fa8a03-6db7-5dce-81da-364cca2c489c":{"reqTiles":["Up","Left"],"inputs":[{"x":0.35,"y":0.0,"balls":[{"type":1,"rate":0.4930521647135417}]},{"x":0.0,"y":0.2,"balls":[{"type":1,"rate":0.4930521647135417}]},{"x":1.0,"y":0.2,"balls":[{"type":2,"rate":0.5294392903645834}]}],"outputs":[{"x":0.35,"y":1.0,"balls":[{"type":1,"rate":0.4930521647135417}]},{"x":0.0,"y":0.65,"balls":[{"type":2,"rate":0.5294392903645834}]},{"x":1.0,"y":0.65,"balls":[{"type":1,"rate":0.4930521647135417}]}],"spec":{}},"84f328aa-abd4-5ee1-97a6-e0987e5be197":{"reqTiles":["Up","Left"],"inputs":[{"x":0.65,"y":0.0,"balls":[{"type":3,"rate":0.5791015625}]},{"x":0.0,"y":0.5,"balls":[{"type":2,"rate":0.26906331380208337}]},{"x":1.0,"y":0.5,"balls":[{"type":1,"rate":0.26906331380208337}]}],"outputs":[{"x":0.5,"y":1.0,"balls":[{"type":2,"rate":0.26906331380208337}]},{"x":0.0,"y":0.35,"balls":[{"type":1,"rate":0.36163330078125}]},{"x":1.0,"y":0.65,"balls":[{"type":3,"rate":0.5791015625}]}],"spec":{}},"3323d3a4-af43-55ef-ac81-e505392a2999":{"reqTiles":["Up","Left"],"inputs":[{"x":0.5,"y":0.0,"balls":[{"type":2,"rate":0.5294392903645834}]},{"x":0.0,"y":0.8,"balls":[{"type":3,"rate":0.8515625}]},{"x":1.0,"y":0.8,"balls":[{"type":1,"rate":0.72119140625}]}],"outputs":[{"x":0.2,"y":1.0,"balls":[{"type":3,"rate":0.8515625}]},{"x":0.0,"y":0.65,"balls":[{"type":1,"rate":0.72265625}]},{"x":1.0,"y":0.5,"balls":[{"type":2,"rate":0.5294392903645834}]}],"spec":{}},"e68dc625-e316-5fa7-bb96-946c013d5bc6":{"reqTiles":["Up"],"inputs":[{"x":0.5,"y":0.0,"balls":[{"type":1,"rate":0.7218017578125}]},{"x":1.0,"y":0.65,"balls":[{"type":2,"rate":0.5294392903645834}]}],"outputs":[{"x":0.2,"y":1.0,"balls":[{"type":2,"rate":0.5294392903645834}]},{"x":1.0,"y":0.8,"balls":[{"type":1,"rate":0.717041015625}]}],"spec":{}},"eb51183b-8683-52ab-9aa8-ba5ae86c1ebb":{"reqTiles":["Up"],"inputs":[{"x":0.65,"y":0.0,"balls":[{"type":4,"rate":0.8359375}]},{"x":1.0,"y":0.35,"balls":[{"type":3,"rate":0.875}]}],"outputs":[{"x":0.65,"y":1.0,"balls":[{"type":3,"rate":0.8515625}]},{"x":1.0,"y":0.5,"balls":[{"type":4,"rate":0.8359375}]}],"spec":{}},"0924ddaf-f48d-53f3-a46f-4f226ce49365":{"reqTiles":["Up"],"inputs":[{"x":0.2,"y":0.0,"balls":[{"type":2,"rate":0.5294392903645834}]},{"x":1.0,"y":0.2,"balls":[{"type":1,"rate":0.4930521647135417}]}],"outputs":[{"x":0.65,"y":1.0,"balls":[{"type":1,"rate":0.542449951171875}]},{"x":1.0,"y":0.35,"balls":[{"type":2,"rate":0.5294392903645834}]}],"spec":{}},"c9c0f96b-2996-51c0-8249-1c75229c0279":{"reqTiles":["Up","Left"],"inputs":[{"x":0.65,"y":0.0,"balls":[{"type":2,"rate":0.5294392903645834}]},{"x":0.0,"y":0.8,"balls":[{"type":3,"rate":0.8515625}]},{"x":1.0,"y":0.5,"balls":[{"type":4,"rate":0.83203125}]}],"outputs":[{"x":0.2,"y":1.0,"balls":[{"type":3,"rate":0.8515625}]},{"x":0.0,"y":0.35,"balls":[{"type":4,"rate":0.83203125}]},{"x":1.0,"y":0.8,"balls":[{"type":2,"rate":0.5294392903645834}]}],"spec":{}},"6135130f-c0f7-5906-b42d-97a4dd259226":{"reqTiles":["Up"],"inputs":[{"x":0.65,"y":0.0,"balls":[{"type":3,"rate":0.8515625}]},{"x":1.0,"y":0.5,"balls":[{"type":1,"rate":0.72265625}]}],"outputs":[{"x":0.2,"y":1.0,"balls":[{"type":1,"rate":0.70068359375}]},{"x":1.0,"y":0.65,"balls":[{"type":3,"rate":0.8515625}]}],"spec":{}},"71d5003c-233a-561b-8197-3f7d236349da":{"reqTiles":["Up","Left"],"inputs":[{"x":0.35,"y":0.0,"balls":[{"type":3,"rate":0.5791015625}]},{"x":0.0,"y":0.8,"balls":[{"type":2,"rate":0.26906331380208337}]}],"outputs":[{"x":0.5,"y":1.0,"balls":[{"type":2,"rate":0.26906331380208337}]},{"x":0.0,"y":0.2,"balls":[{"type":3,"rate":0.5791015625}]}],"spec":{}},"09a7ba04-f605-50b8-af30-6afa9b36d145":{"reqTiles":["Up","Left"],"inputs":[{"x":0.35,"y":0.0,"balls":[{"type":4,"rate":0.83203125}]},{"x":0.0,"y":0.8,"balls":[{"type":2,"rate":0.5294392903645834}]}],"outputs":[{"x":0.5,"y":1.0,"balls":[{"type":2,"rate":0.5294392903645834}]},{"x":0.0,"y":0.5,"balls":[{"type":4,"rate":0.83203125}]}],"spec":{}},"01946434-1eb3-5606-ae49-fcdb01486558":{"reqTiles":["Up","Left"],"inputs":[{"x":0.5,"y":0.0,"balls":[{"type":2,"rate":0.5294392903645834}]},{"x":0.0,"y":0.65,"balls":[{"type":4,"rate":0.833984375}]}],"outputs":[{"x":0.8,"y":1.0,"balls":[{"type":4,"rate":0.833984375}]},{"x":0.0,"y":0.8,"balls":[{"type":2,"rate":0.5294392903645834}]}],"spec":{}},"822c228a-85fe-52f1-8e99-57623d5af3de":{"reqTiles":["Up","Left"],"inputs":[{"x":0.2,"y":0.0,"balls":[{"type":4,"rate":0.83203125}]},{"x":0.0,"y":0.2,"balls":[{"type":2,"rate":0.26906331380208337}]},{"x":1.0,"y":0.8,"balls":[{"type":3,"rate":0.5791015625}]}],"outputs":[{"x":0.5,"y":1.0,"balls":[{"type":2,"rate":0.26906331380208337}]},{"x":0.0,"y":0.5,"balls":[{"type":3,"rate":0.564453125}]},{"x":1.0,"y":0.65,"balls":[{"type":4,"rate":0.83203125}]}],"spec":{}},"96f086c1-e775-5f6f-bc7d-9f555768ea3f":{"reqTiles":["Up","Left"],"inputs":[{"x":0.5,"y":0.0,"balls":[{"type":1,"rate":0.36090087890625}]},{"x":0.0,"y":0.65,"balls":[{"type":3,"rate":0.5791015625}]}],"outputs":[{"x":0.35,"y":1.0,"balls":[{"type":3,"rate":0.5791015625}]},{"x":0.0,"y":0.5,"balls":[{"type":1,"rate":0.26906331380208337}]}],"spec":{}},"26e2cdff-bb2f-5d2b-a346-44ff3eb2321e":{"reqTiles":["Up","Left"],"inputs":[{"x":0.8,"y":0.0,"balls":[{"type":1,"rate":0.717041015625}]},{"x":0.0,"y":0.35,"balls":[{"type":2,"rate":0.5294392903645834}]},{"x":1.0,"y":0.8,"balls":[{"type":1,"rate":0.36090087890625}]}],"outputs":[{"x":0.35,"y":1.0,"balls":[{"type":1,"rate":0.4930521647135417}]},{"x":0.0,"y":0.2,"balls":[{"type":1,"rate":0.4930521647135417}]},{"x":1.0,"y":0.65,"balls":[{"type":2,"rate":0.5294392903645834}]}],"spec":{}},"f73ef623-f2a0-539a-8561-03727dd59386":{"reqTiles":["Up"],"inputs":[{"x":0.2,"y":0.0,"balls":[{"type":1,"rate":0.70068359375}]},{"x":1.0,"y":0.35,"balls":[{"type":4,"rate":0.833984375}]}],"outputs":[{"x":0.35,"y":1.0,"balls":[{"type":4,"rate":0.833984375}]},{"x":1.0,"y":0.65,"balls":[{"type":1,"rate":0.70068359375}]}],"spec":{}},"f078aed9-cd69-56ef-a50b-c954ee945f75":{"reqTiles":["Up"],"inputs":[{"x":0.65,"y":0.0,"balls":[{"type":3,"rate":0.8515625}]},{"x":1.0,"y":0.65,"balls":[{"type":1,"rate":0.72265625}]}],"outputs":[{"x":0.65,"y":1.0,"balls":[{"type":1,"rate":0.70068359375}]},{"x":1.0,"y":0.8,"balls":[{"type":3,"rate":0.8515625}]}],"spec":{}},"b95a3960-b1b0-5abf-bcbd-17c4502e16d3":{"reqTiles":["Up"],"inputs":[{"x":0.8,"y":0.0,"balls":[{"type":3,"rate":0.5791015625}]},{"x":1.0,"y":0.35,"balls":[{"type":1,"rate":0.26906331380208337}]}],"outputs":[{"x":0.2,"y":1.0,"balls":[{"type":1,"rate":0.36163330078125}]},{"x":1.0,"y":0.8,"balls":[{"type":3,"rate":0.5791015625}]}],"spec":{}},"2b00b900-4312-537d-9ece-dc7745242e3b":{"reqTiles":["Up","Left"],"inputs":[{"x":0.35,"y":0.0,"balls":[{"type":1,"rate":0.72119140625}]},{"x":0.0,"y":0.8,"balls":[{"type":4,"rate":0.8359375}]}],"outputs":[{"x":0.65,"y":1.0,"balls":[{"type":4,"rate":0.8359375}]},{"x":0.0,"y":0.35,"balls":[{"type":1,"rate":0.72119140625}]}],"spec":{}},"e57775c3-5b71-5aec-ac2e-cbab60855e5b":{"reqTiles":["Up"],"inputs":[{"x":0.65,"y":0.0,"balls":[{"type":1,"rate":0.7218017578125}]},{"x":1.0,"y":0.5,"balls":[{"type":4,"rate":0.83203125}]}],"outputs":[{"x":0.5,"y":1.0,"balls":[{"type":4,"rate":0.83203125}]},{"x":1.0,"y":0.65,"balls":[{"type":1,"rate":0.7218017578125}]}],"spec":{}},"ad512976-06fa-552f-97e8-39df594fa51d":{"reqTiles":["Up"],"inputs":[{"x":0.5,"y":0.0,"balls":[{"type":2,"rate":0.26906331380208337}]},{"x":1.0,"y":0.2,"balls":[{"type":3,"rate":0.5791015625}]}],"outputs":[{"x":0.2,"y":1.0,"balls":[{"type":3,"rate":0.564453125}]},{"x":1.0,"y":0.8,"balls":[{"type":2,"rate":0.26906331380208337}]}],"spec":{}},"0772cb11-8ad3-5803-8e82-14070b1271b0":{"reqTiles":["Up"],"inputs":[{"x":0.5,"y":0.0,"balls":[{"type":3,"rate":0.5791015625}]}],"outputs":[{"x":0.35,"y":1.0,"balls":[{"type":3,"rate":0.564453125}]}],"spec":{}},"a856dd82-4710-5f57-9cfe-b2eaaa63d088":{"reqTiles":["Up","Left"],"inputs":[{"x":0.65,"y":0.0,"balls":[{"type":1,"rate":0.70068359375}]},{"x":0.0,"y":0.5,"balls":[{"type":4,"rate":0.8359375}]},{"x":1.0,"y":0.8,"balls":[{"type":3,"rate":0.8515625}]}],"outputs":[{"x":0.2,"y":1.0,"balls":[{"type":4,"rate":0.8359375}]},{"x":0.0,"y":0.35,"balls":[{"type":3,"rate":0.875}]},{"x":1.0,"y":0.65,"balls":[{"type":1,"rate":0.72119140625}]}],"spec":{}},"805495ce-0b9b-5f73-815b-911845be22e5":{"reqTiles":["Up","Left"],"inputs":[{"x":0.5,"y":0.0,"balls":[{"type":2,"rate":0.26906331380208337}]},{"x":0.0,"y":0.35,"balls":[{"type":3,"rate":0.564453125}]}],"outputs":[{"x":0.5,"y":1.0,"balls":[{"type":3,"rate":0.564453125}]},{"x":0.0,"y":0.2,"balls":[{"type":2,"rate":0.3585205078125}]}],"spec":{}},"54329d2d-1fbe-55f4-80d7-144ae4ae7664":{"reqTiles":["Up","Left"],"inputs":[{"x":0.2,"y":0.0,"balls":[{"type":4,"rate":0.8359375}]},{"x":0.0,"y":0.65,"balls":[{"type":3,"rate":0.8515625}]},{"x":1.0,"y":0.35,"balls":[{"type":1,"rate":0.72119140625}]}],"outputs":[{"x":0.35,"y":1.0,"balls":[{"type":3,"rate":0.8515625}]},{"x":0.0,"y":0.5,"balls":[{"type":1,"rate":0.72265625}]},{"x":1.0,"y":0.8,"balls":[{"type":4,"rate":0.8359375}]}],"spec":{}},"13f5fefe-141c-59ed-8d50-1d5e28601253":{"reqTiles":["Up"],"inputs":[{"x":0.5,"y":0.0,"balls":[{"type":2,"rate":0.5294392903645834}]}],"outputs":[{"x":0.65,"y":1.0,"balls":[{"type":2,"rate":0.5294392903645834}]}],"spec":{}},"adef3a55-0830-5eee-9afe-37e92e898c74":{"reqTiles":["Up"],"inputs":[{"x":0.35,"y":0.0,"balls":[{"type":1,"rate":0.4930521647135417}]}],"outputs":[{"x":0.35,"y":1.0,"balls":[{"type":1,"rate":0.4930521647135417}]}],"spec":{}},"392996e8-f682-5907-ba9d-9190e3f1bfd9":{"reqTiles":["Up","Left"],"inputs":[{"x":0.5,"y":0.0,"balls":[{"type":2,"rate":0.26906331380208337}]},{"x":0.0,"y":0.8,"balls":[{"type":3,"rate":0.5791015625}]},{"x":1.0,"y":0.2,"balls":[{"type":4,"rate":0.83203125}]},{"x":1.0,"y":0.5,"balls":[{"type":1,"rate":0.36090087890625}]}],"outputs":[{"x":0.5,"y":1.0,"balls":[{"type":4,"rate":0.83203125}]},{"x":0.0,"y":0.35,"balls":[{"type":1,"rate":0.26906331380208337}]},{"x":1.0,"y":0.35,"balls":[{"type":2,"rate":0.26906331380208337}]},{"x":1.0,"y":0.65,"balls":[{"type":3,"rate":0.5791015625}]}],"spec":{}},"0ff29be7-408c-54c4-bdc0-50d7e7c7fdc0":{"reqTiles":["Up","Left"],"inputs":[{"x":0.2,"y":0.0,"balls":[{"type":1,"rate":0.70068359375}]},{"x":0.0,"y":0.5,"balls":[{"type":2,"rate":0.5294392903645834}]}],"outputs":[{"x":0.35,"y":1.0,"balls":[{"type":2,"rate":0.5294392903645834}]},{"x":0.0,"y":0.8,"balls":[{"type":1,"rate":0.72119140625}]}],"spec":{}},"a4fcf729-6f14-57cc-afa6-41f90a932064":{"reqTiles":["Up","Left"],"inputs":[{"x":0.5,"y":0.0,"balls":[{"type":2,"rate":0.5294392903645834}]},{"x":0.0,"y":0.8,"balls":[{"type":1,"rate":0.717041015625}]}],"outputs":[{"x":0.8,"y":1.0,"balls":[{"type":1,"rate":0.717041015625}]},{"x":0.0,"y":0.65,"balls":[{"type":2,"rate":0.5294392903645834}]}],"spec":{}},"1d1618f4-4370-557b-99bc-b7ea31b127f9":{"reqTiles":["Up"],"inputs":[{"x":0.8,"y":0.0,"balls":[{"type":2,"rate":0.26906331380208337}]},{"x":1.0,"y":0.5,"balls":[{"type":3,"rate":0.564453125}]}],"outputs":[{"x":0.8,"y":1.0,"balls":[{"type":3,"rate":0.5791015625}]},{"x":1.0,"y":0.2,"balls":[{"type":2,"rate":0.26906331380208337}]}],"spec":{}},"d81ec14e-6b91-5552-aedc-650ad96768c1":{"reqTiles":["Up"],"inputs":[{"x":0.5,"y":0.0,"balls":[{"type":4,"rate":0.83203125}]}],"outputs":[{"x":0.35,"y":1.0,"balls":[{"type":4,"rate":0.83203125}]}],"spec":{}},"19ad728e-81d9-59c9-9988-e1673b4abb47":{"reqTiles":["Up"],"inputs":[{"x":0.8,"y":0.0,"balls":[{"type":4,"rate":0.83203125}]},{"x":1.0,"y":0.5,"balls":[{"type":3,"rate":0.5791015625}]}],"outputs":[{"x":0.2,"y":1.0,"balls":[{"type":3,"rate":0.564453125}]},{"x":1.0,"y":0.65,"balls":[{"type":4,"rate":0.83203125}]}],"spec":{}},"230c0e6d-955a-50f0-88dd-ef081dfcd71e":{"reqTiles":["Up","Left"],"inputs":[{"x":0.35,"y":0.0,"balls":[{"type":3,"rate":0.8515625}]},{"x":0.0,"y":0.65,"balls":[{"type":1,"rate":0.70068359375}]},{"x":1.0,"y":0.65,"balls":[{"type":4,"rate":0.833984375}]}],"outputs":[{"x":0.5,"y":1.0,"balls":[{"type":1,"rate":0.70068359375}]},{"x":0.0,"y":0.35,"balls":[{"type":4,"rate":0.833984375}]},{"x":1.0,"y":0.8,"balls":[{"type":3,"rate":0.8515625}]}],"spec":{}},"bd8812ef-d7d1-56b0-8f20-6b2875d25480":{"reqTiles":["Up"],"inputs":[{"x":0.35,"y":0.0,"balls":[{"type":2,"rate":0.5294392903645834}]}],"outputs":[{"x":0.5,"y":1.0,"balls":[{"type":2,"rate":0.5294392903645834}]}],"spec":{}},"8b92b372-d655-51b9-80d4-2837640cf884":{"reqTiles":["Up"],"inputs":[{"x":0.2,"y":0.0,"balls":[{"type":3,"rate":0.564453125}]},{"x":1.0,"y":0.2,"balls":[{"type":2,"rate":0.3585205078125}]}],"outputs":[{"x":0.5,"y":1.0,"balls":[{"type":2,"rate":0.26906331380208337}]},{"x":1.0,"y":0.35,"balls":[{"type":3,"rate":0.564453125}]}],"spec":{}},"0a0a4f16-5895-54ff-8048-49be8c4bc6b6":{"reqTiles":["Up"],"inputs":[{"x":0.8,"y":0.0,"balls":[{"type":2,"rate":0.5294392903645834}]}],"outputs":[{"x":0.5,"y":1.0,"balls":[{"type":2,"rate":0.5294392903645834}]}],"spec":{}},"3054242b-b13a-55c4-bd95-6a05868adb45":{"reqTiles":["Up","Left"],"inputs":[{"x":0.2,"y":0.0,"balls":[{"type":3,"rate":0.8515625}]},{"x":0.0,"y":0.65,"balls":[{"type":1,"rate":0.72119140625}]}],"outputs":[{"x":0.35,"y":1.0,"balls":[{"type":1,"rate":0.72119140625}]},{"x":0.0,"y":0.8,"balls":[{"type":3,"rate":0.8515625}]}],"spec":{}},"1524c18c-f853-5047-b059-c7849c81f8ba":{"reqTiles":["Up"],"inputs":[{"x":0.35,"y":0.0,"balls":[{"type":4,"rate":0.83203125}]},{"x":1.0,"y":0.2,"balls":[{"type":3,"rate":0.5791015625}]}],"outputs":[{"x":0.8,"y":1.0,"balls":[{"type":3,"rate":0.5791015625}]},{"x":1.0,"y":0.65,"balls":[{"type":4,"rate":0.83203125}]}],"spec":{}},"7686cc60-0fc9-5e04-99db-1d44ed1e2ae0":{"reqTiles":["Up","Left"],"inputs":[{"x":0.35,"y":0.0,"balls":[{"type":3,"rate":0.59375}]},{"x":0.0,"y":0.65,"balls":[{"type":1,"rate":0.36090087890625}]}],"outputs":[{"x":0.5,"y":1.0,"balls":[{"type":1,"rate":0.36090087890625}]},{"x":0.0,"y":0.35,"balls":[{"type":3,"rate":0.564453125}]}],"spec":{}},"e97133ed-e31a-5170-8ed0-7f948a59c9fc":{"reqTiles":["Up","Left"],"inputs":[{"x":0.35,"y":0.0,"balls":[{"type":3,"rate":0.564453125}]},{"x":0.0,"y":0.65,"balls":[{"type":4,"rate":0.83203125}]}],"outputs":[{"x":0.8,"y":1.0,"balls":[{"type":4,"rate":0.83203125}]},{"x":0.0,"y":0.2,"balls":[{"type":3,"rate":0.5791015625}]}],"spec":{}},"427dbba0-a53f-5a80-8cbf-d896307e3a69":{"reqTiles":["Up"],"inputs":[{"x":0.5,"y":0.0,"balls":[{"type":4,"rate":0.83203125}]}],"outputs":[{"x":0.2,"y":1.0,"balls":[{"type":4,"rate":0.83203125}]}],"spec":{}},"adf43796-a920-5ca6-9eb1-969b1d568a37":{"reqTiles":["Up"],"inputs":[{"x":0.65,"y":0.0,"balls":[{"type":1,"rate":0.542449951171875}]}],"outputs":[{"x":0.8,"y":1.0,"balls":[{"type":1,"rate":0.541351318359375}]}],"spec":{}},"51896da3-1b29-55e3-945a-81ccd44380a1":{"reqTiles":["Up","Left"],"inputs":[{"x":0.8,"y":0.0,"balls":[{"type":3,"rate":0.59375}]},{"x":0.0,"y":0.35,"balls":[{"type":1,"rate":0.36090087890625}]},{"x":1.0,"y":0.35,"balls":[{"type":3,"rate":0.564453125}]}],"outputs":[{"x":0.65,"y":1.0,"balls":[{"type":3,"rate":0.5791015625}]},{"x":0.0,"y":0.8,"balls":[{"type":3,"rate":0.5791015625}]},{"x":1.0,"y":0.65,"balls":[{"type":1,"rate":0.36090087890625}]}],"spec":{}},"d37c633b-ed20-5379-ba82-a800a3b2c23c":{"reqTiles":["Up"],"inputs":[{"x":0.65,"y":0.0,"balls":[{"type":2,"rate":0.5294392903645834}]}],"outputs":[{"x":0.5,"y":1.0,"balls":[{"type":2,"rate":0.5294392903645834}]}],"spec":{}},"c5b8809f-0f74-5f23-9e0a-68f860de3dfb":{"reqTiles":["Up"],"inputs":[{"x":0.2,"y":0.0,"balls":[{"type":4,"rate":0.83203125}]}],"outputs":[{"x":0.35,"y":1.0,"balls":[{"type":4,"rate":0.83203125}]}],"spec":{}},"c970d90d-a52f-59f9-87f3-6f4309232479":{"reqTiles":["Up","Left"],"inputs":[{"x":0.65,"y":0.0,"balls":[{"type":4,"rate":0.8359375}]},{"x":0.0,"y":0.8,"balls":[{"type":3,"rate":0.8515625}]},{"x":1.0,"y":0.35,"balls":[{"type":4,"rate":0.83203125}]}],"outputs":[{"x":0.35,"y":1.0,"balls":[{"type":4,"rate":0.833984375}]},{"x":0.0,"y":0.65,"balls":[{"type":4,"rate":0.833984375}]},{"x":1.0,"y":0.8,"balls":[{"type":3,"rate":0.8515625}]}],"spec":{}}}