{"puzzle":{"reqTiles":["Up"],"inputs":[{"x":0.65,"y":0.0,"balls":[{"type":4,"rate":1.0}]}],"outputs":[{"x":0.35,"y":1.0,"balls":[{"type":4,"rate":1.0}]}],"spec":{}},"blueprint":{"puzzle":"483edd7c-7065-5d5a-b117-76ba147c8836","title":"CERn","submittedAt":"2024-04-07T23:04:24.07539804Z","widgets":{"32":{"angle":-1.1334156349418734,"type":"brick","x":103,"y":297},"96":{"height":10,"type":"repulsor","width":150,"x":304,"y":381},"1":{"angle":0.3017532204234924,"type":"board","x":504,"y":77},"33":{"angle":-0.963188392390124,"type":"brick","x":216,"y":308},"97":{"height":10,"type":"repulsor","width":150,"x":270,"y":354},"34":{"angle":-1.3215248549771457,"type":"brick","x":195,"y":359},"98":{"height":10,"type":"repulsor","width":150,"x":353,"y":425},"3":{"angle":-3.047431040784648,"type":"fan","x":678,"y":546},"35":{"angle":-2.0041632763708153,"type":"brick","x":201,"y":409},"99":{"height":10,"type":"repulsor","width":150,"x":307,"y":386},"4":{"angle":-1.238121667212421,"type":"fan","x":86,"y":514},"36":{"angle":-1.6364536748833074,"type":"brick","x":442,"y":346},"100":{"height":10,"type":"repulsor","width":150,"x":326,"y":330},"5":{"angle":-1.3529708867147887,"type":"fan","x":141,"y":583},"37":{"angle":-1.5267915682642097,"type":"brick","x":516,"y":408},"101":{"height":10,"type":"repulsor","width":150,"x":270,"y":376},"6":{"angle":0,"type":"board","x":342,"y":179},"38":{"angle":1.5063972872018327,"type":"brick","x":449,"y":405},"7":{"angle":-0.5849932592362722,"type":"board","x":170,"y":235},"39":{"angle":-1.6199672103155482,"type":"brick","x":515,"y":356},"71":{"angle":-0.9329687104100267,"type":"brick","x":261,"y":635},"103":{"angle":-3.145167072291616,"type":"fan","x":631,"y":538},"8":{"angle":-1.5607966601082317,"type":"board","x":97.5,"y":376},"40":{"angle":0,"type":"brick","x":373,"y":493},"72":{"angle":-0.934095793230413,"type":"brick","x":423,"y":460},"9":{"angle":0.5088460493266527,"type":"board","x":175,"y":511},"41":{"angle":0.28073814628883803,"type":"brick","x":265,"y":564},"73":{"angle":-1.3939660773854783,"type":"brick","x":241,"y":695},"10":{"angle":8.79947636313116e-3,"type":"board","x":330,"y":568},"42":{"angle":0,"type":"brick","x":306,"y":480},"74":{"angle":-0.7318778949381332,"type":"brick","x":386,"y":594},"11":{"angle":-0.5737099069238952,"type":"board","x":614,"y":526},"43":{"angle":-2.058495858726022,"type":"brick","x":105,"y":469},"75":{"angle":-0.6680502644849262,"type":"brick","x":477,"y":647},"12":{"angle":-2.237568701170466,"type":"fan","x":334,"y":617},"44":{"angle":0.8784618921218662,"type":"brick","x":418,"y":296},"76":{"angle":-0.6439180070459515,"type":"brick","x":523,"y":609},"13":{"angle":-3.1817378861214647,"type":"fan","x":709,"y":451},"45":{"angle":0.2773210489442378,"type":"brick","x":366,"y":261},"77":{"angle":-0.3573340483160212,"type":"board","x":381,"y":693.967},"14":{"angle":-1.7105052010840598,"type":"fan","x":137,"y":543},"46":{"angle":0,"type":"brick","x":315,"y":251},"78":{"height":10,"type":"repulsor","width":150,"x":329,"y":343},"15":{"angle":1.4316771579928547,"type":"fan","x":379,"y":125},"47":{"angle":-0.4341358844493618,"type":"brick","x":255,"y":265},"79":{"height":10,"type":"repulsor","width":150,"x":315,"y":371},"16":{"angle":-0.23210664122926486,"type":"fan","x":85,"y":249},"80":{"height":10,"type":"repulsor","width":150,"x":311,"y":349},"17":{"angle":-1.904779786763822,"type":"fan","x":249,"y":618},"49":{"angle":0.209715728107743,"type":"fan","x":195,"y":137},"81":{"height":10,"type":"repulsor","width":150,"x":315,"y":399},"18":{"angle":0,"type":"fan","x":44,"y":259},"50":{"angle":-1.0090446748723354,"type":"fan","x":73.5,"y":435},"82":{"height":10,"type":"repulsor","width":150,"x":338,"y":383},"19":{"angle":-0.2817570096295481,"type":"fan","x":39,"y":335},"51":{"angle":-1.451486485994413,"type":"fan","x":121,"y":541},"83":{"height":10,"type":"repulsor","width":150,"x":319,"y":350},"20":{"angle":-0.7783121142011652,"type":"fan","x":43.062275,"y":429},"52":{"angle":-1.4204731450365786,"type":"fan","x":107,"y":582},"84":{"height":10,"type":"repulsor","width":150,"x":314,"y":371},"53":{"angle":1.5024884439782034,"type":"fan","x":478,"y":162},"85":{"height":10,"type":"repulsor","width":150,"x":296,"y":346},"54":{"angle":1.4498764332405831,"type":"fan","x":434,"y":136},"86":{"height":10,"type":"repulsor","width":150,"x":316,"y":370},"55":{"angle":-2.3956012632044352,"type":"fan","x":353,"y":612},"87":{"height":10,"type":"repulsor","width":150,"x":296,"y":317},"56":{"angle":-1.8113828102676712,"type":"fan","x":197,"y":593},"88":{"height":10,"type":"repulsor","width":150,"x":326,"y":363},"25":{"angle":0.9171103245682548,"type":"board","x":489,"y":254},"57":{"angle":0.7266423406817257,"type":"fan","x":303,"y":131},"89":{"height":10,"type":"repulsor","width":150,"x":332,"y":395},"58":{"angle":0.542016753999821,"type":"fan","x":259,"y":129},"90":{"height":10,"type":"repulsor","width":150,"x":317,"y":375},"59":{"angle":0.2621025075006999,"type":"fan","x":181,"y":167},"91":{"height":10,"type":"repulsor","width":150,"x":297,"y":368},"28":{"angle":0.5012395518535105,"type":"brick","x":243,"y":458},"60":{"angle":0,"type":"fan","x":136,"y":196},"92":{"height":10,"type":"repulsor","width":150,"x":279,"y":406},"29":{"angle":-1.598075058482107,"type":"brick","x":514,"y":310},"93":{"height":10,"type":"repulsor","width":150,"x":286,"y":340},"30":{"angle":0.2769238636948105,"type":"brick","x":412,"y":186},"94":{"height":10,"type":"repulsor","width":150,"x":319,"y":337},"31":{"angle":-0.3432947229756879,"type":"brick","x":247,"y":183},"95":{"height":10,"type":"repulsor","width":150,"x":274,"y":343}}},"snapshot":{"balls":[{"age":695,"angle":1.432977318763733,"type":4,"va":-31.9711971282959,"vx":5.464119911193848,"vy":1.9879571199417114,"x":6.731246471405029,"y":-13.8510160446167},{"age":16,"angle":-2.685485601425171,"type":4,"va":2.0900418758392334,"vx":-0.3954915404319763,"vy":-0.7268068194389343,"x":5.161876678466797,"y":-14.717226028442383},{"age":389,"angle":-2.629782199859619,"type":4,"va":46.580379486083984,"vx":0.40780937671661377,"vy":1.0090453624725342,"x":5.928903102874756,"y":-13.748276710510254},{"age":323,"angle":1.6105462312698364,"type":4,"va":40.66098403930664,"vx":-18.384090423583984,"vy":4.784806251525879,"x":4.917857646942139,"y":-10.389749526977539},{"age":265,"angle":-2.000114917755127,"type":4,"va":-8.952878952026367,"vx":5.67767471075058e-2,"vy":-4.712023735046387,"x":12.514270782470703,"y":-7.483238220214844},{"age":182,"angle":-0.44719433784484863,"type":4,"va":-8.76692008972168,"vx":1.3082844018936157,"vy":-0.4979742765426636,"x":11.882794380187988,"y":-1.7481920719146729},{"age":133,"angle":0.15904739499092102,"type":4,"va":-8.752967834472656,"vx":1.292801022529602,"vy":-0.4023946523666382,"x":11.208908081054688,"y":-1.5370073318481445},{"age":56,"angle":-0.9751944541931152,"type":4,"va":-4.450319766998291,"vx":0.8014482259750366,"vy":-0.2402001917362213,"x":9.778369903564453,"y":-0.9654730558395386},{"age":22,"angle":-0.17667128145694733,"type":4,"va":0.1362999528646469,"vx":0.1035509929060936,"vy":-0.7229391932487488,"x":9.58950138092041,"y":-8.11978280544281e-2}],"widgets":{}}}