{"puzzle":{"reqTiles":["Up","Left"],"inputs":[{"x":0.35,"y":0.0,"balls":[{"type":3,"rate":0.5}]},{"x":0.0,"y":0.35,"balls":[{"type":4,"rate":1.0}]}],"outputs":[{"x":0.8,"y":1.0,"balls":[{"type":4,"rate":1.0}]},{"x":0.0,"y":0.65,"balls":[{"type":3,"rate":0.40625}]}],"spec":{}},"blueprint":{"puzzle":"66a8d12a-2d28-53c2-9bfc-52e571f8cb47","title":"6 fans and a cat","submittedAt":"2024-04-11T06:54:30.933569912Z","widgets":{"64":{"height":85,"type":"repulsor","width":85,"x":697.5,"y":42.5},"128":{"angle":0,"type":"brick","x":288,"y":726.5},"1":{"angle":-1.4285080138210577e-2,"type":"fan","x":91,"y":138},"129":{"angle":0,"type":"brick","x":449,"y":702},"161":{"angle":1.5552030963828727,"type":"brick","x":14.0285048,"y":561},"162":{"angle":1.5881953646699174,"type":"brick","x":14.0896465,"y":622},"67":{"angle":0,"type":"brick","x":131,"y":709},"99":{"angle":-2.32539800575442e-2,"type":"ballstand","x":203,"y":400},"163":{"angle":1.581960782778332,"type":"brick","x":13.8787424,"y":683},"68":{"angle":0,"type":"brick","x":156,"y":726.5},"132":{"angle":0,"type":"brick","x":256,"y":702},"164":{"angle":0,"type":"brick","x":382,"y":523},"5":{"angle":0,"type":"fan","x":78,"y":137},"69":{"angle":0,"type":"brick","x":99,"y":726.5},"101":{"angle":-1.275637746738534,"type":"hammer","x":188,"y":499},"133":{"angle":0,"type":"brick","x":482,"y":726.5},"165":{"angle":0,"type":"brick","x":482,"y":410},"6":{"angle":0,"type":"fan","x":66,"y":138},"166":{"angle":0,"type":"brick","x":34,"y":703.5},"7":{"angle":0,"type":"fan","x":55,"y":137},"103":{"angle":0,"type":"brick","x":34,"y":162},"8":{"angle":0,"sticker":"cat","type":"sticker","x":46,"y":110},"105":{"angle":0,"type":"brick","x":459,"y":434},"137":{"angle":0,"type":"brick","x":415,"y":632},"169":{"angle":0,"sticker":"determinism","type":"sticker","x":351,"y":684},"74":{"angle":3.894938125011264e-3,"catMass":2,"type":"catswat","x":474,"y":377},"138":{"angle":0,"type":"brick","x":440,"y":656},"170":{"angle":0,"type":"brick","x":287,"y":682},"107":{"angle":-1.5687106625180982,"type":"board","x":729.3150415,"y":357},"139":{"angle":0,"type":"brick","x":376,"y":656},"171":{"angle":0,"type":"brick","x":322,"y":704},"44":{"angle":-0.5284209116606385,"type":"board","x":80.10288,"y":489},"108":{"angle":-1.5867830871307549,"type":"board","x":700.5,"y":145},"140":{"angle":0,"type":"brick","x":312,"y":656},"172":{"angle":0,"type":"brick","x":352,"y":682},"45":{"angle":-7.534755391329179e-2,"type":"board","x":373,"y":252},"109":{"angle":1.5804114150945998,"type":"board","x":715,"y":253},"173":{"angle":0,"type":"brick","x":413,"y":681},"46":{"angle":-0.829586005493995,"type":"board","x":674.2827945,"y":669.378821},"174":{"angle":0,"type":"brick","x":386,"y":703},"15":{"angle":-3.1581389405522793,"type":"prism","x":258,"y":43.8131432},"47":{"angle":0.8135037147078972,"type":"board","x":507,"y":670.2312245},"79":{"angle":0,"sticker":"figure1-happy","type":"sticker","x":130,"y":629},"111":{"angle":0,"type":"brick","x":34,"y":368},"143":{"angle":0,"type":"brick","x":410,"y":610},"175":{"angle":0,"type":"brick","x":354,"y":726.5},"16":{"angle":1.5711009686097284,"type":"prism","x":43.0150243,"y":259},"48":{"angle":0,"type":"prism","x":592,"y":697},"80":{"angle":-3.149027460834991,"type":"anvil","x":127,"y":641},"112":{"angle":1.5786267663215126,"type":"brick","x":13.765811,"y":119},"144":{"angle":0,"type":"brick","x":367,"y":611},"176":{"angle":0,"type":"brick","x":417,"y":726.5},"113":{"angle":0,"type":"brick","x":34,"y":74},"177":{"angle":0,"type":"brick","x":350,"y":626.5},"50":{"angle":-8.111107226458619e-2,"type":"board","x":307,"y":274},"114":{"angle":1.5975774086565113,"type":"brick","x":14.4055987,"y":389},"146":{"angle":0,"type":"brick","x":67,"y":704},"51":{"angle":-9.158021054627105e-2,"type":"board","x":238,"y":298},"115":{"angle":0,"type":"brick","x":223,"y":726.5},"147":{"angle":0,"type":"brick","x":411,"y":568},"52":{"angle":-8.640514938993807e-2,"type":"board","x":438,"y":230},"116":{"angle":0,"type":"brick","x":482,"y":704},"148":{"angle":0,"type":"brick","x":367,"y":591},"85":{"angle":-1.5703926894121245,"type":"sword","x":592,"y":589},"117":{"angle":0,"type":"brick","x":220,"y":679},"149":{"angle":0,"type":"brick","x":411,"y":592},"118":{"angle":0,"type":"brick","x":248,"y":657},"150":{"angle":0,"type":"brick","x":409,"y":547},"55":{"angle":1.556368805766838,"type":"board","x":729.7385735,"y":527},"87":{"height":107,"type":"repulsor","width":107,"x":591.5,"y":510.5},"119":{"angle":0,"type":"brick","x":286,"y":633},"151":{"angle":0,"type":"brick","x":463,"y":681},"56":{"angle":1.551460253555351,"type":"board","x":448,"y":528},"120":{"angle":0,"type":"brick","x":302,"y":611},"152":{"angle":0,"type":"brick","x":34,"y":726.5},"121":{"angle":0,"type":"brick","x":325,"y":591},"153":{"angle":0,"type":"brick","x":194,"y":701},"122":{"angle":0,"type":"brick","x":346,"y":569},"27":{"angle":1.572174032183042,"type":"prism","x":43.0681507,"y":481},"123":{"angle":0,"type":"brick","x":361,"y":545},"92":{"height":157,"type":"repulsor","width":157,"x":86,"y":542},"124":{"angle":0,"type":"brick","x":407,"y":524},"125":{"angle":0,"type":"brick","x":419,"y":478},"126":{"angle":0,"type":"brick","x":408,"y":500},"63":{"angle":-1.6633782641841286,"type":"fan","x":198,"y":334},"127":{"angle":0,"type":"brick","x":440,"y":455},"159":{"angle":-0.970030661268612,"type":"fan","x":44.2178015,"y":325}}},"snapshot":{"balls":[{"age":483,"angle":-0.6209003329277039,"type":4,"va":3.065861225128174,"vx":-0.4480138421058655,"vy":-0.16334141790866852,"x":5.639612197875977,"y":-4.845816135406494},{"age":492,"angle":-2.668196201324463,"type":3,"va":-4.551840782165527,"vx":-0.585121214389801,"vy":-1.7179136276245117,"x":0.4119780957698822,"y":-9.50287914276123},{"age":434,"angle":0.23314228653907776,"type":4,"va":-8.922690391540527,"vx":-0.4381563365459442,"vy":-1.2855138778686523,"x":11.82574462890625,"y":-14.420228004455566},{"age":365,"angle":-1.8394533395767212,"type":4,"va":20.853984832763672,"vx":-2.339393377304077,"vy":-2.3291845321655273,"x":12.4210844039917,"y":-14.036233901977539},{"age":316,"angle":-1.6099392175674438,"type":4,"va":-13.975287437438965,"vx":2.5061018466949463,"vy":-0.33051443099975586,"x":9.482717514038086,"y":-12.168034553527832},{"age":247,"angle":3.034355640411377,"type":4,"va":13.68961238861084,"vx":-0.8444873094558716,"vy":-2.6813881397247314,"x":14.135302543640137,"y":-10.46776294708252},{"age":227,"angle":-1.795218825340271,"type":3,"va":11.287252426147461,"vx":-1.780331015586853,"vy":-0.2904779314994812,"x":2.947666645050049,"y":-5.787749767303467},{"age":150,"angle":1.0990450382232666,"type":4,"va":-2.673431158065796,"vx":-2.3885629177093506,"vy":-8.8671875,"x":11.894153594970703,"y":-5.8287787437438965},{"age":102,"angle":-3.0591466426849365,"type":4,"va":-2.502542018890381,"vx":28.48560333251953,"vy":7.482915878295898,"x":5.348196506500244,"y":-2.6657142639160156},{"age":126,"angle":-1.6790711879730225,"type":3,"va":5.970913887023926,"vx":-0.9495429992675781,"vy":-3.987159579992294e-2,"x":4.526463508605957,"y":-5.271507740020752},{"age":57,"angle":-2.541973352432251,"type":4,"va":-7.338148593902588,"vx":1.6223570108413696,"vy":-1.064175009727478,"x":0.45642387866973877,"y":-5.249532222747803},{"age":51,"angle":-1.792507290840149,"type":3,"va":-2.4243111610412598,"vx":0.21707122027873993,"vy":-6.661270618438721,"x":5.181027889251709,"y":-2.343585968017578}],"widgets":{"74":{"angle":-3.8949381560087204e-3,"key":"74","va":0,"vx":0,"vy":0,"x":9.479999542236328,"y":-7.539999961853027}}}}