{"puzzle":{"reqTiles":["Up","Left"],"inputs":[{"x":0.2,"y":0.0,"balls":[{"type":1,"rate":0.717041015625}]},{"x":0.0,"y":0.5,"balls":[{"type":2,"rate":0.5381266276041667}]}],"outputs":[{"x":0.35,"y":1.0,"balls":[{"type":2,"rate":0.5381266276041667}]},{"x":0.0,"y":0.2,"balls":[{"type":1,"rate":0.7232666015625}]}],"spec":{}},"blueprint":{"puzzle":"0d399313-1d22-5e66-8d8a-27b03ee7770d","title":"round the back way","submittedAt":"2024-04-26T10:37:20.5263579Z","widgets":{"0":{"angle":0.45212011605857594,"type":"board","x":189,"y":150},"32":{"angle":-0.714893158653335,"type":"board","x":570,"y":171},"64":{"angle":0.13264340764453603,"type":"brick","x":333,"y":676},"1":{"angle":-0.6583987372788164,"type":"brick","x":83,"y":132},"33":{"angle":0,"type":"board","x":652.5,"y":113},"65":{"angle":0,"type":"board","x":371.5,"y":567},"2":{"angle":-0.8690508183962684,"type":"brick","x":132,"y":85},"34":{"angle":0,"type":"board","x":564,"y":112},"66":{"angle":0,"type":"board","x":652.5,"y":562},"3":{"angle":0,"type":"board","x":393,"y":194},"35":{"angle":-1.5988490500156003,"type":"fan","x":601,"y":366},"67":{"angle":-0.31964535705144387,"type":"brick","x":703.480097,"y":661.5},"4":{"angle":1.2177672668778627,"type":"board","x":38.697395,"y":484},"36":{"angle":0,"type":"fan","x":448,"y":240},"68":{"angle":1.561399199808266,"type":"board","x":730.1781594,"y":571},"5":{"angle":0.45103220132047467,"type":"brick","x":98,"y":588},"37":{"angle":-1.6107418600891676,"type":"brick","x":442,"y":413},"69":{"angle":-0.2672677102944994,"type":"brick","x":658,"y":675},"6":{"angle":0.7668739377445457,"type":"board","x":320,"y":294},"38":{"angle":0,"type":"brick","x":459,"y":369},"70":{"angle":3.145656754041005,"type":"fan","x":191,"y":187},"7":{"angle":-1.3850328951278614,"type":"brick","x":294,"y":663},"39":{"angle":0,"type":"brick","x":218,"y":258},"8":{"angle":0.693168964452973,"type":"brick","x":192,"y":661},"40":{"angle":0,"type":"brick","x":706,"y":385},"9":{"angle":1.5629371668975987,"type":"brick","x":214,"y":705.8949564},"41":{"angle":0,"type":"brick","x":614,"y":446},"10":{"angle":0.7223842092285672,"type":"brick","x":147,"y":623},"42":{"angle":0,"type":"brick","x":706,"y":215},"11":{"angle":-1.5688901464415912,"type":"board","x":477,"y":104},"43":{"angle":0,"type":"brick","x":679,"y":164},"12":{"angle":-1.5810000542888505,"type":"board","x":384,"y":103},"44":{"angle":0,"type":"brick","x":692,"y":215},"13":{"angle":-0.11137859272836798,"type":"board","x":652.041818,"y":494},"45":{"angle":-1.5805846837236341,"type":"brick","x":692,"y":180},"14":{"angle":1.1283121667015117,"type":"board","x":514,"y":236},"46":{"angle":0,"type":"brick","x":616,"y":164},"15":{"angle":-1.079526265593583e-2,"type":"board","x":509,"y":346},"47":{"angle":-1.7097298893419135,"type":"fan","x":401,"y":533},"79":{"angle":0,"type":"board","x":396,"y":111},"16":{"angle":0,"type":"board","x":443,"y":270},"48":{"angle":0,"type":"board","x":263,"y":408},"80":{"angle":0.9039987563604012,"type":"board","x":235,"y":471},"17":{"angle":-0.6969506619676079,"type":"board","x":430,"y":232},"49":{"angle":0,"type":"board","x":87.5,"y":336},"81":{"angle":0,"type":"board","x":287,"y":531},"18":{"angle":0,"type":"board","x":340,"y":348},"50":{"angle":1.59647217515494,"type":"brick","x":181,"y":367},"82":{"angle":0,"type":"board","x":276,"y":485},"19":{"angle":1.5766989813647612,"type":"board","x":259,"y":267},"51":{"angle":-1.5966803497302238,"type":"fan","x":229,"y":433},"83":{"angle":1.5718000545908866,"type":"brick","x":451,"y":543},"20":{"angle":0,"type":"brick","x":601,"y":222},"52":{"angle":-1.9354173756776138,"type":"fan","x":157,"y":369},"84":{"angle":0,"type":"brick","x":34,"y":574},"21":{"angle":0,"type":"brick","x":602,"y":243},"53":{"angle":1.5831552480722768,"type":"brick","x":71,"y":294},"85":{"angle":-0.53189464367752,"type":"brick","x":482,"y":711.121374},"22":{"angle":2.8769038817592765e-2,"type":"brick","x":603,"y":267},"54":{"angle":1.5739705718255703,"type":"brick","x":65,"y":230},"86":{"angle":0,"type":"brick","x":34,"y":675},"23":{"angle":0,"type":"brick","x":481,"y":13.5},"55":{"angle":-1.528160561043313,"type":"fan","x":38.4675483,"y":304},"87":{"angle":-1.590536628475685,"type":"brick","x":80,"y":705.7401535},"24":{"angle":0,"type":"brick","x":381,"y":13.5},"56":{"angle":0,"type":"board","x":478,"y":643},"88":{"angle":0,"type":"brick","x":542,"y":726.5},"25":{"angle":1.385110345246283,"type":"board","x":360,"y":484},"57":{"angle":1.2838960790934464e-2,"type":"board","x":373,"y":729.8773605},"89":{"angle":0,"type":"brick","x":542,"y":716},"26":{"angle":0,"type":"board","x":515,"y":448},"58":{"angle":0,"type":"brick","x":541,"y":692},"90":{"angle":-1.5738974817872846,"type":"brick","x":638,"y":705.9583045},"27":{"angle":0.6682441751868671,"type":"board","x":136,"y":204},"59":{"angle":0,"type":"brick","x":631,"y":607},"91":{"angle":0,"type":"brick","x":166,"y":675},"28":{"angle":-1.571783388475978,"type":"board","x":681,"y":309},"60":{"angle":-0.2501188640796355,"type":"board","x":515,"y":623},"92":{"angle":0,"type":"brick","x":99,"y":674},"29":{"angle":1.5472290146297514,"type":"board","x":630,"y":346},"61":{"angle":-1.5611812384951933,"type":"brick","x":562,"y":538},"30":{"angle":0,"type":"board","x":484,"y":504},"62":{"angle":0,"type":"board","x":652.5,"y":688},"31":{"angle":1.21505562108278,"type":"board","x":609,"y":357}}},"snapshot":{"balls":[{"age":1676,"angle":2.4291536808013916,"type":2,"va":11.996553421020508,"vx":-1.9053282737731934,"vy":-0.9422529935836792,"x":9.620841026306152,"y":-13.718905448913574},{"age":1268,"angle":2.054962158203125,"type":2,"va":8.434731483459473,"vx":-1.3372193574905396,"vy":1.716652698814869e-2,"x":7.129331588745117,"y":-14.254921913146973},{"age":1177,"angle":1.2003589868545532,"type":1,"va":0.8985679149627686,"vx":-0.4578901529312134,"vy":-0.648950457572937,"x":0.32154616713523865,"y":-2.9127237796783447},{"age":1036,"angle":0.9548180103302002,"type":1,"va":9.357592582702637,"vx":-1.1258931159973145,"vy":-0.2754344940185547,"x":1.8686739206314087,"y":-3.8607091903686523},{"age":955,"angle":2.4118638038635254,"type":1,"va":6.550678253173828,"vx":-1.0405784845352173,"vy":1.862645149230957e-9,"x":6.051181316375732,"y":-7.8215651512146},{"age":890,"angle":-1.0608221292495728,"type":1,"va":0,"vx":0,"vy":0,"x":13.38538932800293,"y":-3.871302604675293},{"age":846,"angle":-2.211967945098877,"type":2,"va":19.101980209350586,"vx":-2.7291197776794434,"vy":-1.9369664192199707,"x":8.742036819458008,"y":-14.25932788848877},{"age":833,"angle":-0.15261897444725037,"type":1,"va":-7.919990539550781,"vx":-3.95780086517334,"vy":3.8328423500061035,"x":2.883324384689331,"y":-5.78952693939209},{"age":780,"angle":-1.801312804222107,"type":2,"va":7.0885796546936035,"vx":-1.125345230102539,"vy":1.4447204768657684e-2,"x":6.754889965057373,"y":-14.250053405761719},{"age":714,"angle":-1.470717430114746,"type":1,"va":-1.4091460704803467,"vx":0.18198497593402863,"vy":0.14188675582408905,"x":6.728435039520264,"y":-7.820190906524658},{"age":662,"angle":-2.6237385272979736,"type":2,"va":4.627109050750732,"vx":-0.7363096475601196,"vy":9.313225746154785e-10,"x":10.183784484863281,"y":-13.411444664001465},{"age":595,"angle":1.3376539945602417,"type":1,"va":12.399784088134766,"vx":-1.9665143489837646,"vy":-3.270000219345093e-2,"x":9.819592475891113,"y":-9.741816520690918},{"age":538,"angle":-1.0073091983795166,"type":2,"va":-1.1173688173294067,"vx":0.17804677784442902,"vy":1.4551915228366852e-9,"x":11.704548835754395,"y":-13.421311378479004},{"age":552,"angle":-2.489328145980835,"type":1,"va":12.550192832946777,"vx":-1.9787287712097168,"vy":-2.5899408385157585e-2,"x":9.492925643920898,"y":-9.741966247558594},{"age":453,"angle":-0.4020967483520508,"type":2,"va":4.622124195098877,"vx":-0.6861372590065002,"vy":-0.557349681854248,"x":12.08842945098877,"y":-13.377464294433594},{"age":493,"angle":0.22293616831302643,"type":1,"va":5.202978610992432,"vx":-0.8222503662109375,"vy":-9.19622853398323e-2,"x":13.953902244567871,"y":-9.437246322631836},{"age":451,"angle":-1.9972199201583862,"type":1,"va":2.1382267475128174,"vx":-0.3384462594985962,"vy":-3.785381838679314e-2,"x":13.170233726501465,"y":-9.52474594116211},{"age":310,"angle":2.629011631011963,"type":2,"va":12.425058364868164,"vx":-2.706859827041626,"vy":0.5890678763389587,"x":13.458040237426758,"y":-12.710707664489746},{"age":187,"angle":2.1013731956481934,"type":2,"va":-40.127838134765625,"vx":5.978066444396973,"vy":6.684483587741852e-2,"x":7.259121894836426,"y":-12.16390323638916},{"age":205,"angle":2.1391186714172363,"type":1,"va":-24.583026885986328,"vx":3.894698143005371,"vy":-2.3375917226076126e-2,"x":10.25298023223877,"y":-6.581753253936768},{"age":121,"angle":1.8012372255325317,"type":2,"va":-28.351804733276367,"vx":5.78709602355957,"vy":0.1708185374736786,"x":2.6333978176116943,"y":-11.005163192749023},{"age":127,"angle":-0.41996949911117554,"type":1,"va":-4.143697738647461,"vx":-1.000049352645874,"vy":-3.1153650283813477,"x":5.750879287719727,"y":-4.207700729370117},{"age":47,"angle":-0.5662479996681213,"type":1,"va":-11.15689754486084,"vx":1.9477704763412476,"vy":-1.2618235349655151,"x":3.2319817543029785,"y":-0.9936765432357788}],"widgets":{}}}